[
  {
    "type": "overmap_terrain",
    "id": "ftl_beacon",
    "name": "FTL Beacon",
    "sym": "#",
    "color": "yellow",
    "see_cost": 1
  },

  {
    "type": "overmap_terrain",
    "id": "ftl_beacon_around_space",
    "name": "field",
    "sym": ".",
    "color": "yellow",
    "see_cost": 1
  },
  
  {
    "type": "palette",
    "id": "ftl_beacon_palette",
    "terrain": {
      " ": [ [ "t_grass_dead", 3 ], [ "t_grass", 15 ], [ "t_dirt", 5 ] ],
      "-": [ "t_linoleum_white_no_roof" ],
      "=": [ "t_sand" ],
      "I": [ "t_sand" ],
      "#": [ "t_floor_noroof" ]
    },
    "fields": {
    },
    "items": {
        "I": { "item": "ftl_beacon_drop_item_group", "chance": 10,  "repeat": [ 1, 1 ] }
    },
    "monster": {
    }
  },
  
  {
    "type": "mapgen",
    "method": "json",
    "om_terrain": [ "ftl_beacon" ],
    "weight": 100,
    "object": {
      "rows": [
        "                        ",
        "           --           ",
        "           --           ",
        "         --##--         ",
        "         --##--         ",
        "       --##===I--       ",
        "       --##=I==--       ",
        "     --##========--     ",
        "     --##======I=--     ",
        "   --##===I========--   ",
        "   --##=I==========--   ",
        " --##========I=======-- ",
        " --##==I===========I=-- ",
        "   --===========I==--   ",
        "   --I====I========--   ",
        "     --========I=--     ",
        "     --=I===I====--     ",
        "       --======--       ",
        "       --======--       ",
        "         --I=--         ",
        "         --==--         ",
        "           --           ",
        "           --           ",
        "                        "
      ],
      "palettes": [ "ftl_beacon_palette" ]
    }
  },
  
    
  {
    "type": "mapgen",
    "method": "json",
    "om_terrain": [ "ftl_beacon_around_space" ],
    "weight": 100,
    "object": {
      "rows": [
        "                        ",
        "                        ",
        "                        ",
        "                        ",
        "                        ",
        "                        ",
        "                        ",
        "                        ",
        "                        ",
        "                        ",
        "                        ",
        "                        ",
        "                        ",
        "                        ",
        "                        ",
        "                        ",
        "                        ",
        "                        ",
        "                        ",
        "                        ",
        "                        ",
        "                        ",
        "                        ",
        "                        "
      ],
      "palettes": [ "ftl_beacon_palette" ]
    }
  }
  
  

]
